pythonvideoannotator_module_timeline/__init__.py
pythonvideoannotator_module_timeline/module.py
pythonvideoannotator_module_timeline/models/__init__.py
pythonvideoannotator_module_timeline/models/project_timeline.py
Python_video_annotator_module_timeline-0.6.26.dist-info/METADATA
Python_video_annotator_module_timeline-0.6.26.dist-info/WHEEL
Python_video_annotator_module_timeline-0.6.26.dist-info/top_level.txt
Python_video_annotator_module_timeline-0.6.26.dist-info/RECORD
